cli/__init__.py
cli/main.py
cli/commands/__init__.py
cli/commands/wasm_build.py
cli/commands/wasm_detect.py
cli/commands/wasm_dev.py
cli/commands/wasm_doctor.py
cli/commands/wasm_info.py
cli/commands/wasm_init.py
cli/commands/wasm_run.py
cli/commands/wasm_serve.py
cli/commands/wasm_test.py
engine/__init__.py
engine/wasm_builder.py
engine/wasm_dev_server.py
engine/wasm_optimizer.py
engine/builders/__init__.py
engine/builders/base.py
engine/builders/wasm_builder_factory.py
engine/builders/wasm_cpp_builder.py
engine/builders/wasm_go_builder.py
engine/builders/wasm_js_builder.py
engine/builders/wasm_python_builder.py
engine/builders/wasm_rust_builder.py
server/__init__.py
server/wasm_http_server.py
server/wasm_http_server_cli.py
system/__init__.py
system/wasm_docker.py
system/wasm_health.py
utils/__init__.py
utils/build_cache.py
utils/structured_logger.py
utils/wasm_component_runner.py
utils/wasm_deps.py
utils/wasm_detect.py
utils/wasm_errors.py
utils/wasm_logger.py
utils/wasm_script.py
utils/wasm_security.py
utils/wasm_welcome.py
utils/wasm_wit.py
wazo-0.1.0.dist-info/licenses/LICENSE
wazo-0.1.0.dist-info/METADATA
wazo-0.1.0.dist-info/WHEEL
wazo-0.1.0.dist-info/entry_points.txt
wazo-0.1.0.dist-info/top_level.txt
wazo-0.1.0.dist-info/RECORD
