Metadata-Version: 2.4
Name: wazo
Version: 0.1.0
Summary: WAZO: The Docker of WebAssembly - Build any codebase to WASM with zero setup
Author-email: Daichi Toyoda <daichi.toyoda7@gmail.com>
License: MIT
Project-URL: Homepage, https://github.com/wazo/wazo
Project-URL: Documentation, https://wazo.readthedocs.io
Project-URL: Repository, https://github.com/wazo/wazo
Project-URL: Issues, https://github.com/wazo/wazo/issues
Keywords: wasm,webassembly,compiler,rust,python,javascript,typescript,component-model,docker
Classifier: Development Status :: 4 - Beta
Classifier: Intended Audience :: Developers
Classifier: License :: OSI Approved :: MIT License
Classifier: Programming Language :: Python :: 3
Classifier: Programming Language :: Python :: 3.8
Classifier: Programming Language :: Python :: 3.9
Classifier: Programming Language :: Python :: 3.10
Classifier: Programming Language :: Python :: 3.11
Classifier: Programming Language :: Python :: 3.12
Classifier: Topic :: Software Development :: Compilers
Classifier: Topic :: Software Development :: Build Tools
Requires-Python: >=3.8
License-File: LICENSE
Requires-Dist: click>=8.0.0
Requires-Dist: docker>=6.0.0
Requires-Dist: rich>=13.0.0
Requires-Dist: pydantic>=2.0.0
Requires-Dist: tomli>=2.0.0; python_version < "3.11"
Requires-Dist: wasmtime>=14.0.0
Requires-Dist: flask>=3.0.0
Requires-Dist: flask-cors>=4.0.0
Requires-Dist: watchdog>=3.0.0
Provides-Extra: dev
Requires-Dist: pytest>=7.0.0; extra == "dev"
Requires-Dist: pytest-cov>=4.0.0; extra == "dev"
Requires-Dist: black>=23.0.0; extra == "dev"
Requires-Dist: ruff>=0.1.0; extra == "dev"
Requires-Dist: mypy>=1.0.0; extra == "dev"
Requires-Dist: isort>=5.12.0; extra == "dev"
Dynamic: license-file
